loginsights/__init__.py
loginsights/main.py
loginsights-0.0.7.dist-info/METADATA
loginsights-0.0.7.dist-info/WHEEL
loginsights-0.0.7.dist-info/licenses/LICENSE
loginsights-0.0.7.dist-info/RECORD
