Metadata-Version: 2.4
Name: loginsights
Version: 0.0.7
Summary: This is a powerful library handling the formatting of application logs and metrics to the LogInsights platform.
Project-URL: Homepage, https://www.loginsights.studio/
Project-URL: Issues, https://github.com/pypa/sampleproject/issues
Author-email: Owner <cdewind123@gmail.com>
License-Expression: MIT
License-File: LICENSE
Classifier: Operating System :: OS Independent
Classifier: Programming Language :: Python :: 3
Requires-Python: >=3.12
Requires-Dist: azure-core==1.32.0
Requires-Dist: azure-storage-queue==12.12.0
Requires-Dist: certifi==2025.1.31
Requires-Dist: cffi==1.17.1
Requires-Dist: charset-normalizer==3.4.1
Requires-Dist: cryptography==44.0.0
Requires-Dist: idna==3.10
Requires-Dist: isodate==0.7.2
Requires-Dist: pycparser==2.22
Requires-Dist: requests==2.32.3
Requires-Dist: six==1.17.0
Requires-Dist: typing-extensions==4.12.2
Requires-Dist: urllib3==2.3.0
